deep_chainmap/__init__.py
deep_chainmap-0.1.3.dist-info/licenses/LICENSE
deep_chainmap-0.1.3.dist-info/WHEEL
deep_chainmap-0.1.3.dist-info/METADATA
deep_chainmap-0.1.3.dist-info/RECORD
