Metadata-Version: 2.4
Name: deep_chainmap
Version: 0.1.3
Summary: A recursive subclass of `collections.ChainMap`
Author: C.M.T. Robert
Requires-Python: >=3.9
License-Expression: MIT
Classifier: Intended Audience :: Developers
Classifier: Programming Language :: Python :: 3
Classifier: Programming Language :: Python :: 3.9
Classifier: Programming Language :: Python :: 3.10
Classifier: Programming Language :: Python :: 3.11
Classifier: Programming Language :: Python :: 3.12
Classifier: Programming Language :: Python :: 3.13
License-File: LICENSE
Project-URL: Homepage, https://github.com/neutrinoceros/deep_chainmap
